hooks/__init__.py
hooks/commands.py
hooks/githooks.py
hooks/main.py
hooks-0.1.1.dist-info/DESCRIPTION.rst
hooks-0.1.1.dist-info/METADATA
hooks-0.1.1.dist-info/RECORD
hooks-0.1.1.dist-info/WHEEL
hooks-0.1.1.dist-info/entry_points.txt
hooks-0.1.1.dist-info/metadata.json
hooks-0.1.1.dist-info/top_level.txt
